[
{ "CustomerName": "ป้านา", "Phones": "081-387-1342, 081-024-9476", "Type": "Credit", "Order": "1" },
{ "CustomerName": "มณี บ้านแพะ", "Phones": "083-321-0905", "Type": "Cash", "Order": "2" },
{ "CustomerName": "ชัยศิริ", "Phones": "081-472-4018", "Type": "Cash", "Order": "3" },
{ "CustomerName": "ป้ากัญญา", "Phones": "054-263-079", "Type": "Cash", "Order": "4" },
{ "CustomerName": "ร้านขายยา แจ้ซ้อน", "Phones": "054-263-000", "Type": "Cash", "Order": "5" },
{ "CustomerName": "บุญส่ง", "Phones": "085-154-7366", "Type": "Cash", "Order": "6" },
{ "CustomerName": "วรรณ แจ้ซ้อน", "Phones": "085-797-6956", "Type": "Cash", "Order": "7" },
{ "CustomerName": "ผ่องพรรณ", "Phones": "054-263-001", "Type": "Cash", "Order": "8" },
{ "CustomerName": "ป้ามอญ", "Phones": "054-263-047", "Type": "Credit", "Order": "9" },
{ "CustomerName": "แดงข้างทิม", "Phones": "099-153-6979 , 054-271418", "Type": "Credit", "Order": "10" },
{ "CustomerName": "ติ๋ม", "Phones": "054-369-246, 087-190-0889", "Type": "Credit", "Order": "11" },
{ "CustomerName": "ป้าบัวเขียว", "Phones": "085-029-9269", "Type": "Cash", "Order": "12" },
{ "CustomerName": "แอ๊ด", "Phones": "089-559-1588", "Type": "Cash", "Order": "13" },
{ "CustomerName": "พ่อวุ้น", "Phones": "085-058-9628", "Type": "Cash", "Order": "14" },
{ "CustomerName": "ป้าต้อย ใหม่ผ้าขาว", "Phones": "086-192-8916", "Type": "Cash", "Order": "15" },
{ "CustomerName": "ไพรวัลย์", "Phones": "089-556-2781", "Type": "Credit", "Order": "16" },
{ "CustomerName": "ผ่าน", "Phones": "087-182-9978", "Type": "Cash", "Order": "17" },
{ "CustomerName": "แม่สุก", "Phones": "084-950-9612", "Type": "Cash", "Order": "18" },
{ "CustomerName": "ป้าหวั๋น", "Phones": "054-271-067", "Type": "Credit", "Order": "19" },
{ "CustomerName": "ยุ้ย", "Phones": "082-890-7298, 081-028-5463", "Type": "Cash", "Order": "20" },
{ "CustomerName": "แมว ข้างยุ้ย", "Phones": "084-803-6969", "Type": "Cash", "Order": "21" },
{ "CustomerName": "ดวงพร", "Phones": "086-181-6244", "Type": "Cash", "Order": "22" },
{ "CustomerName": "พร", "Phones": "083-860-2553", "Type": "Credit", "Order": "23" },
{ "CustomerName": "สหกรณ์บ้านแป้น", "Phones": "081-961-8050, 054-369206", "Type": "Cash", "Order": "24" },
{ "CustomerName": "ก๋วยเตี๋ยวไก่", "Phones": "080-061-4469", "Type": "Cash", "Order": "25" },
{ "CustomerName": "วรรณ แจ้ห่ม", "Phones": "054-369-766, 083-154-2805", "Type": "Credit", "Order": "26" },
{ "CustomerName": "ป้าทอน สบหก", "Phones": "087-186-4428", "Type": "Cash", "Order": "27" },
{ "CustomerName": "ปรีชา ปลาเผา", "Phones": "086-066-8579, 093-281-4642", "Type": "Cash", "Order": "28" },
{ "CustomerName": "สมร", "Phones": "081-288-0089, 054-369420", "Type": "Cash", "Order": "29" },
{ "CustomerName": "กุ้ง บ้านสา", "Phones": "098-797-0873", "Type": "Cash", "Order": "30" },
{ "CustomerName": "แม่ศรีนวล หมี่กรอบ", "Phones": "087-728-2823", "Type": "Cash", "Order": "31" }
]